[
  {
    "case_id": 0,
    "solver": "structural",
    "params": {
      "bore_mm": 80.81749399636251,
      "stroke_mm": 90.57317566149044,
      "compression_ratio": 12.84115737238901,
      "rpm": 3953.750963820813,
      "load_fraction": 0.6578401639343888
    },
    "success": true,
    "outputs": {
      "von_mises_max": null,
      "calibration": {
        "von_mises_max_mpa": 33.72995,
        "displacement_max_mm": 0.05,
        "safety_factor": 8.301227840539342
      }
    }
  },
  {
    "case_id": 0,
    "solver": "thermal",
    "params": {
      "bore_mm": 80.81749399636251,
      "stroke_mm": 90.57317566149044,
      "compression_ratio": 12.84115737238901,
      "rpm": 3953.750963820813,
      "load_fraction": 0.6578401639343888
    },
    "success": true,
    "outputs": {
      "T_crown_max": 520.0,
      "calibration": {
        "T_crown_max_K": 520.0,
        "T_liner_max_K": 430.0,
        "htc_gas_avg_w_m2k": 1200.0
      }
    }
  },
  {
    "case_id": 1,
    "solver": "structural",
    "params": {
      "bore_mm": 85.94098440323248,
      "stroke_mm": 93.34598178645663,
      "compression_ratio": 12.364740671676374,
      "rpm": 3224.1906465394004,
      "load_fraction": 0.786835258981639
    },
    "success": true,
    "outputs": {
      "von_mises_max": null,
      "calibration": {
        "von_mises_max_mpa": 19.27426,
        "displacement_max_mm": 0.05,
        "safety_factor": 14.527146567494679
      }
    }
  },
  {
    "case_id": 1,
    "solver": "thermal",
    "params": {
      "bore_mm": 85.94098440323248,
      "stroke_mm": 93.34598178645663,
      "compression_ratio": 12.364740671676374,
      "rpm": 3224.1906465394004,
      "load_fraction": 0.786835258981639
    },
    "success": true,
    "outputs": {
      "T_crown_max": 520.0,
      "calibration": {
        "T_crown_max_K": 520.0,
        "T_liner_max_K": 430.0,
        "htc_gas_avg_w_m2k": 1200.0
      }
    }
  },
  {
    "case_id": 2,
    "solver": "structural",
    "params": {
      "bore_mm": 82.62772439409282,
      "stroke_mm": 91.78477589641501,
      "compression_ratio": 11.373425290502391,
      "rpm": 2549.183482716292,
      "load_fraction": 0.6870760209572173
    },
    "success": true,
    "outputs": {
      "von_mises_max": null,
      "calibration": {
        "von_mises_max_mpa": 14.45569,
        "displacement_max_mm": 0.05,
        "safety_factor": 19.369535456280538
      }
    }
  },
  {
    "case_id": 2,
    "solver": "thermal",
    "params": {
      "bore_mm": 82.62772439409282,
      "stroke_mm": 91.78477589641501,
      "compression_ratio": 11.373425290502391,
      "rpm": 2549.183482716292,
      "load_fraction": 0.6870760209572173
    },
    "success": true,
    "outputs": {
      "T_crown_max": 520.0,
      "calibration": {
        "T_crown_max_K": 520.0,
        "T_liner_max_K": 430.0,
        "htc_gas_avg_w_m2k": 1200.0
      }
    }
  },
  {
    "case_id": 3,
    "solver": "structural",
    "params": {
      "bore_mm": 88.6317802258771,
      "stroke_mm": 88.1252596820697,
      "compression_ratio": 11.885873217976426,
      "rpm": 2062.5053075089845,
      "load_fraction": 0.8624509568062068
    },
    "success": true,
    "outputs": {
      "von_mises_max": null,
      "calibration": {
        "von_mises_max_mpa": 45.37482,
        "displacement_max_mm": 0.05,
        "safety_factor": 6.170823377370974
      }
    }
  },
  {
    "case_id": 3,
    "solver": "thermal",
    "params": {
      "bore_mm": 88.6317802258771,
      "stroke_mm": 88.1252596820697,
      "compression_ratio": 11.885873217976426,
      "rpm": 2062.5053075089845,
      "load_fraction": 0.8624509568062068
    },
    "success": true,
    "outputs": {
      "T_crown_max": 520.0,
      "calibration": {
        "T_crown_max_K": 520.0,
        "T_liner_max_K": 430.0,
        "htc_gas_avg_w_m2k": 1200.0
      }
    }
  },
  {
    "case_id": 4,
    "solver": "structural",
    "params": {
      "bore_mm": 87.61066846823572,
      "stroke_mm": 85.29959232769647,
      "compression_ratio": 11.55056246448625,
      "rpm": 3001.1468018463615,
      "load_fraction": 0.7301452479250241
    },
    "success": true,
    "outputs": {
      "von_mises_max": null,
      "calibration": {
        "von_mises_max_mpa": 195.955,
        "displacement_max_mm": 0.05,
        "safety_factor": 1.428899492230359
      }
    }
  },
  {
    "case_id": 4,
    "solver": "thermal",
    "params": {
      "bore_mm": 87.61066846823572,
      "stroke_mm": 85.29959232769647,
      "compression_ratio": 11.55056246448625,
      "rpm": 3001.1468018463615,
      "load_fraction": 0.7301452479250241
    },
    "success": true,
    "outputs": {
      "T_crown_max": 520.0,
      "calibration": {
        "T_crown_max_K": 520.0,
        "T_liner_max_K": 430.0,
        "htc_gas_avg_w_m2k": 1200.0
      }
    }
  }
]